{
  "author": "kalanis",
  "name": "kw_auth_groups",
  "description": "Groups for determine authentication rights in KWCMS",
  "source": "https://github.com/alex-kalanis/kw_auth_groups",
  "license": "BSD-3-Clause",
  "require": {
    "php": ">=7.2.0"
  },
  "suggest": {
    "alex-kalanis/kw_auth_sources": "dev-master",
    "alex-kalanis/kw_auth_groups": "dev-master",
    "alex-kalanis/kw_paths": "dev-master"
  },
  "require-dev": {
    "alex-kalanis/kw_locks": "dev-master"
  },
  "minimum-stability": "dev",
  "prefer-stable": true
}